dataformat/sansllb_nexus.py
pygdatax/__init__.py
pygdatax/cansas.py
pygdatax/flib.py
pygdatax/gui_reflectivity.py
pygdatax/icons.py
pygdatax/moduledescription.py
pygdatax/nxlib.py
pygdatax/xeussredauto.py
pygdatax/gui/__init__.py
pygdatax/gui/customsilx.py
pygdatax/gui/dataviewer.py
pygdatax/gui/gui_log.py
pygdatax/gui/gui_rxxeuss.py
pygdatax/gui/gui_sans.py
pygdatax/gui/gui_sans_llb.py
pygdatax/gui/gui_survey.py
pygdatax/gui/gui_xeuss.py
pygdatax/gui/treatmenttable.py
pygdatax/gui/test/__init__.py
pygdatax/gui/test/test_gui_xeuss.py
pygdatax/instruments/__init__.py
pygdatax/instruments/sans.py
pygdatax/instruments/sansllb.py
pygdatax/instruments/xeuss.py
pygdatax/instruments/xeussrx.py
pygdatax/instruments/test/__init__.py
pygdatax/instruments/test/test_sans.py
pygdatax/resources/__init__.py
pygdatax/resources/beam.ico
pygdatax/resources/check.ico
pygdatax/resources/clipboard.ico
pygdatax/resources/concat.ico
pygdatax/resources/cross.ico
pygdatax/resources/dark.ico
pygdatax/resources/directory.ico
pygdatax/resources/empty_cell.ico
pygdatax/resources/gear.ico
pygdatax/resources/logo_llb.ico
pygdatax/resources/mask.ico
pygdatax/resources/nxs2text.ico
pygdatax/resources/refresh.ico
pygdatax/resources/target.ico
pygdatax/test/__init__.py
pygdatax/test/test_paxy.py
pygdatax-0.2.12.dist-info/LICENSE.txt
pygdatax-0.2.12.dist-info/METADATA
pygdatax-0.2.12.dist-info/WHEEL
pygdatax-0.2.12.dist-info/entry_points.txt
pygdatax-0.2.12.dist-info/top_level.txt
pygdatax-0.2.12.dist-info/RECORD
