Metadata-Version: 2.2
Name: pygdatax
Version: 0.2.12
Summary: Python libray for Small Angle Neutron (SANS) and X-ray (SAXS) scattering data treatment and visualization.
Author-email: Alexis Chenneviere <alexis.chenneviere@cea.fr>
Keywords: SAXS,SANS,XRR,data reduction
Requires-Python: >=3.10
License-File: LICENSE.txt
Requires-Dist: silx
Requires-Dist: matplotlib
Requires-Dist: scipy
Requires-Dist: pyFAI
Requires-Dist: nexusformat
Requires-Dist: openpyxl
Requires-Dist: pyyaml
Requires-Dist: ipython
Requires-Dist: lmfit
Provides-Extra: full
Requires-Dist: PyQt5; extra == "full"
